{
  "cik": "0001976908",
  "entityType": "other",
  "sic": "8200",
  "sicDescription": "Services-Educational Services",
  "ownerOrg": "07 Trade & Services",
  "insiderTransactionForOwnerExists": 0,
  "insiderTransactionForIssuerExists": 0,
  "name": "JIADE Ltd",
  "tickers": [
    "JDZG"
  ],
  "exchanges": [
    "Nasdaq"
  ],
  "ein": "000000000",
  "lei": null,
  "description": "",
  "website": "",
  "investorWebsite": "",
  "category": "Non-accelerated filer<br>Emerging growth company",
  "fiscalYearEnd": "1231",
  "stateOfIncorporation": "E9",
  "stateOfIncorporationDescription": "Cayman Islands",
  "addresses": {
    "mailing": {
      "street1": "UNIT 2-02, PUNINGDUN BUSINESS PLAZA",
      "street2": "NO.1702&1706 MINJIANG RD, JINJIAN DIST.",
      "city": "CHENGDU CITY, SICHUAN PROVINCE",
      "stateOrCountry": null,
      "zipCode": "610000",
      "stateOrCountryDescription": null,
      "isForeignLocation": 1,
      "foreignStateTerritory": null,
      "country": "China",
      "countryCode": "F4"
    },
    "business": {
      "street1": "UNIT 2-02, PUNINGDUN BUSINESS PLAZA",
      "street2": "NO.1702&1706 MINJIANG RD, JINJIAN DIST.",
      "city": "CHENGDU CITY, SICHUAN PROVINCE",
      "stateOrCountry": null,
      "zipCode": "610000",
      "stateOrCountryDescription": null,
      "isForeignLocation": 1,
      "foreignStateTerritory": null,
      "country": "China",
      "countryCode": "F4"
    }
  },
  "phone": "400-028-0776",
  "flags": "",
  "formerNames": [],
  "filings": {
    "recent": {
      "accessionNumber": [
        "0001104659-25-089538",
        "9999999995-25-002697",
        "0001104659-25-079631",
        "0001104659-25-078583",
        "0001104659-25-069022",
        "0001104659-25-068083",
        "0001213900-25-063243",
        "0000000000-25-007257",
        "0001104659-25-065783",
        "0001104659-25-060901",
        "0001104659-25-052421",
        "0001104659-25-045026",
        "0001410578-25-000919",
        "0001104659-25-015656",
        "0001104659-25-005240",
        "0001104659-24-131954",
        "0001104659-24-130904",
        "0001104659-24-123677",
        "0001104659-24-119216",
        "0001104659-24-118886",
        "0001104659-24-118885",
        "0001104659-24-115298",
        "0001104659-24-085364",
        "0001104659-24-062982",
        "0001104659-24-062423",
        "9999999995-24-001522",
        "0001354457-24-000334",
        "0001104659-24-059585",
        "0001104659-24-059577",
        "0001104659-24-059568",
        "0001104659-24-047671",
        "0001104659-24-032899",
        "0001104659-24-032893",
        "0000000000-24-002591",
        "0001104659-24-024789",
        "0001104659-24-024485",
        "0001104659-24-024477",
        "0000000000-24-001753",
        "0001104659-24-007087",
        "0001104659-24-007080",
        "0000000000-24-000922",
        "0001104659-23-129525",
        "0001104659-23-118503",
        "0001104659-23-118501",
        "0000000000-23-011383",
        "0001104659-23-102783",
        "0001104659-23-102781",
        "0000000000-23-009648",
        "0001104659-23-087141"
      ],
      "filingDate": [
        "2025-09-12",
        "2025-08-20",
        "2025-08-18",
        "2025-08-14",
        "2025-07-18",
        "2025-07-15",
        "2025-07-11",
        "2025-07-10",
        "2025-07-03",
        "2025-06-20",
        "2025-05-23",
        "2025-05-06",
        "2025-04-25",
        "2025-02-20",
        "2025-01-22",
        "2024-12-27",
        "2024-12-20",
        "2024-11-27",
        "2024-11-14",
        "2024-11-14",
        "2024-11-14",
        "2024-11-07",
        "2024-08-02",
        "2024-05-17",
        "2024-05-16",
        "2024-05-14",
        "2024-05-14",
        "2024-05-10",
        "2024-05-10",
        "2024-05-10",
        "2024-04-16",
        "2024-03-11",
        "2024-03-11",
        "2024-03-08",
        "2024-02-16",
        "2024-02-15",
        "2024-02-15",
        "2024-02-14",
        "2024-01-26",
        "2024-01-26",
        "2024-01-23",
        "2023-12-27",
        "2023-11-15",
        "2023-11-15",
        "2023-10-18",
        "2023-09-21",
        "2023-09-21",
        "2023-08-31",
        "2023-08-03"
      ],
      "reportDate": [
        "",
        "",
        "",
        "",
        "2025-07-18",
        "",
        "",
        "",
        "",
        "2025-06-20",
        "2025-05-23",
        "2025-05-06",
        "2024-12-31",
        "2025-02-20",
        "2025-01-22",
        "2024-12-27",
        "2024-12-20",
        "2024-11-27",
        "",
        "",
        "",
        "2024-11-07",
        "2024-08-02",
        "2024-05-17",
        "",
        "",
        "",
        "",
        "",
        "",
        "",
        "",
        "",
        "",
        "",
        "",
        "",
        "",
        "",
        "",
        "",
        "",
        "",
        "",
        "",
        "",
        "",
        "",
        ""
      ],
      "acceptanceDateTime": [
        "2025-09-12T20:05:29.000Z",
        "2025-08-21T04:16:11.000Z",
        "2025-08-18T15:25:24.000Z",
        "2025-08-14T20:07:48.000Z",
        "2025-07-18T20:05:31.000Z",
        "2025-07-16T18:56:51.000Z",
        "2025-07-11T20:00:04.000Z",
        "2025-07-10T15:36:10.000Z",
        "2025-07-03T20:06:05.000Z",
        "2025-06-20T12:00:17.000Z",
        "2025-05-23T20:05:17.000Z",
        "2025-05-06T20:02:01.000Z",
        "2025-04-25T20:01:43.000Z",
        "2025-02-20T21:05:07.000Z",
        "2025-01-22T21:05:05.000Z",
        "2024-12-27T13:00:12.000Z",
        "2024-12-20T22:01:41.000Z",
        "2024-11-27T21:05:21.000Z",
        "2024-11-14T22:05:03.000Z",
        "2024-11-14T21:05:23.000Z",
        "2024-11-14T21:05:14.000Z",
        "2024-11-07T21:05:22.000Z",
        "2024-08-02T20:10:14.000Z",
        "2024-05-17T20:05:17.000Z",
        "2024-05-16T17:39:53.000Z",
        "2024-05-15T04:15:12.000Z",
        "2024-05-14T12:11:32.000Z",
        "2024-05-10T10:04:35.000Z",
        "2024-05-10T10:03:01.000Z",
        "2024-05-10T10:01:54.000Z",
        "2024-04-16T17:17:32.000Z",
        "2024-03-11T17:12:29.000Z",
        "2024-03-11T17:11:41.000Z",
        "2024-03-08T20:36:11.000Z",
        "2024-02-16T16:34:42.000Z",
        "2024-02-15T20:42:11.000Z",
        "2024-02-15T20:37:57.000Z",
        "2024-02-14T15:36:06.000Z",
        "2024-01-26T17:00:50.000Z",
        "2024-01-26T16:51:47.000Z",
        "2024-01-23T23:36:06.000Z",
        "2023-12-27T15:53:32.000Z",
        "2023-11-15T15:13:37.000Z",
        "2023-11-15T15:08:15.000Z",
        "2023-10-18T15:36:11.000Z",
        "2023-09-21T19:10:25.000Z",
        "2023-09-21T19:08:32.000Z",
        "2023-08-31T17:32:22.000Z",
        "2023-08-03T15:18:21.000Z"
      ],
      "act": [
        "33",
        "33",
        "",
        "33",
        "34",
        "33",
        "34",
        "",
        "33",
        "34",
        "34",
        "34",
        "34",
        "34",
        "34",
        "34",
        "34",
        "34",
        "34",
        "34",
        "34",
        "34",
        "34",
        "34",
        "33",
        "33",
        "34",
        "34",
        "",
        "",
        "33",
        "",
        "33",
        "",
        "34",
        "",
        "33",
        "",
        "",
        "33",
        "",
        "33",
        "",
        "33",
        "",
        "",
        "33",
        "",
        "33"
      ],
      "form": [
        "424B1",
        "EFFECT",
        "CORRESP",
        "F-1",
        "6-K",
        "S-8",
        "SCHEDULE 13G/A",
        "UPLOAD",
        "DRS",
        "6-K",
        "6-K",
        "6-K",
        "20-F",
        "6-K",
        "6-K",
        "6-K",
        "6-K",
        "6-K",
        "SC 13G",
        "SC 13G",
        "SC 13G",
        "6-K",
        "6-K",
        "6-K",
        "424B4",
        "EFFECT",
        "CERT",
        "8-A12B",
        "CORRESP",
        "CORRESP",
        "F-1/A",
        "CORRESP",
        "F-1/A",
        "UPLOAD",
        "FWP",
        "CORRESP",
        "F-1/A",
        "UPLOAD",
        "CORRESP",
        "F-1/A",
        "UPLOAD",
        "F-1",
        "DRSLTR",
        "DRS/A",
        "UPLOAD",
        "DRSLTR",
        "DRS/A",
        "UPLOAD",
        "DRS"
      ],
      "fileNumber": [
        "333-288704",
        "333-289601",
        "",
        "333-289601",
        "001-42098",
        "333-288704",
        "005-94738",
        "377-08179",
        "377-08179",
        "001-42098",
        "001-42098",
        "001-42098",
        "001-42098",
        "001-42098",
        "001-42098",
        "001-42098",
        "001-42098",
        "001-42098",
        "005-94738",
        "005-94738",
        "005-94738",
        "001-42098",
        "001-42098",
        "001-42098",
        "333-276283",
        "333-276283",
        "001-42098",
        "001-42098",
        "",
        "",
        "333-276283",
        "",
        "333-276283",
        "377-06797",
        "333-276283",
        "",
        "333-276283",
        "377-06797",
        "",
        "333-276283",
        "377-06797",
        "333-276283",
        "",
        "377-06797",
        "377-06797",
        "",
        "377-06797",
        "377-06797",
        "377-06797"
      ],
      "filmNumber": [
        "251311512",
        "251238275",
        "",
        "251218925",
        "251134544",
        "251127163",
        "251118953",
        "",
        "251105587",
        "251059116",
        "25982111",
        "25917096",
        "25873658",
        "25645231",
        "25545938",
        "241582430",
        "241568782",
        "241511003",
        "241464079",
        "241461879",
        "241461847",
        "241435504",
        "241171059",
        "24959534",
        "24954617",
        "24946866",
        "24941534",
        "24932715",
        "",
        "",
        "24846972",
        "",
        "24737331",
        "",
        "24646432",
        "",
        "24643567",
        "",
        "",
        "24565938",
        "",
        "231515426",
        "",
        "231409346",
        "",
        "",
        "231268966",
        "",
        "231138682"
      ],
      "items": [
        "",
        ",,",
        "",
        "",
        "",
        "",
        "",
        "",
        "",
        "",
        "",
        "",
        "",
        "",
        "",
        "",
        "",
        "",
        "",
        "",
        "",
        "",
        "",
        "",
        "",
        "F-1,,2024-05-14 16:30:00",
        "",
        "",
        "",
        "",
        "",
        "",
        "",
        "",
        "",
        "",
        "",
        "",
        "",
        "",
        "",
        "",
        "",
        "",
        "",
        "",
        "",
        "",
        ""
      ],
      "core_type": [
        "424B1",
        "EFFECT",
        "CORRESP",
        "F-1",
        "6-K",
        "S-8",
        "SCHEDULE 13G/A",
        "LETTER",
        "DRS",
        "6-K",
        "6-K",
        "6-K",
        "XBRL",
        "6-K",
        "6-K",
        "6-K",
        "6-K",
        "6-K",
        "SC 13G",
        "SC 13G",
        "SC 13G",
        "6-K",
        "6-K",
        "6-K",
        "424B4",
        "EFFECT",
        "CERT",
        "8-A12B",
        "CORRESP",
        "CORRESP",
        "F-1/A",
        "CORRESP",
        "F-1/A",
        "LETTER",
        "FWP",
        "CORRESP",
        "F-1/A",
        "LETTER",
        "CORRESP",
        "F-1/A",
        "LETTER",
        "F-1",
        "DRSLTR",
        "DRS/A",
        "LETTER",
        "DRSLTR",
        "DRS/A",
        "LETTER",
        "DRS"
      ],
      "size": [
        707750,
        1869,
        8322,
        1305477,
        10255,
        757812,
        7309,
        40626,
        814525,
        13306,
        37655,
        1148506,
        11899628,
        17705,
        55793,
        80538,
        19376,
        382706,
        67937,
        54087,
        55116,
        10224,
        18970,
        399573,
        4774058,
        1875,
        217778,
        15109,
        11321,
        25636,
        4929435,
        37740,
        6194518,
        46140,
        3502888,
        23952,
        6558850,
        42303,
        14722,
        6674311,
        44439,
        7339858,
        21663,
        6204891,
        47268,
        60059,
        5230353,
        68552,
        5002299
      ],
      "isXBRL": [
        0,
        0,
        0,
        1,
        0,
        0,
        0,
        0,
        0,
        0,
        0,
        0,
        1,
        0,
        0,
        0,
        0,
        0,
        0,
        0,
        0,
        0,
        0,
        0,
        0,
        0,
        0,
        0,
        0,
        0,
        0,
        0,
        0,
        0,
        0,
        0,
        0,
        0,
        0,
        0,
        0,
        0,
        0,
        0,
        0,
        0,
        0,
        0,
        0
      ],
      "isInlineXBRL": [
        0,
        0,
        0,
        1,
        0,
        0,
        0,
        0,
        0,
        0,
        0,
        0,
        1,
        0,
        0,
        0,
        0,
        0,
        0,
        0,
        0,
        0,
        0,
        0,
        0,
        0,
        0,
        0,
        0,
        0,
        0,
        0,
        0,
        0,
        0,
        0,
        0,
        0,
        0,
        0,
        0,
        0,
        0,
        0,
        0,
        0,
        0,
        0,
        0
      ],
      "primaryDocument": [
        "tm2519332-4_424b1.htm",
        "xslEFFECTX01/primary_doc.xml",
        "filename1.htm",
        "tm2519332-2_f1.htm",
        "tm2521218d1_6k.htm",
        "tm2520608d1_s8.htm",
        "xslSCHEDULE_13G_X01/primary_doc.xml",
        "filename1.pdf",
        "filename1.htm",
        "tm2517165d1_6k.htm",
        "tm2516056d1_6k.htm",
        "tm2513932d1_6k.htm",
        "jdzg-20241231x20f.htm",
        "tm256986d1_6k.htm",
        "tm254113d1_6k.htm",
        "tm2432029d1_6k.htm",
        "tm2431641d1_6k.htm",
        "tm2429499d1_6k.htm",
        "tm2428358d3_sc13g.htm",
        "tm2428358d2_sc13g.htm",
        "tm2428358d1_sc13g.htm",
        "tm2427802d1_6k.htm",
        "tm2420718d1_6k.htm",
        "tm2414815d1_6k.htm",
        "tm2321027-20_424b4.htm",
        "xslEFFECTX01/primary_doc.xml",
        "8A_Cert_JDZG.pdf",
        "tm2321027d22_8a12b.htm",
        "filename1.htm",
        "filename1.htm",
        "tm2321027-18_f1a.htm",
        "filename1.htm",
        "tm2321027-14_f1a.htm",
        "filename1.pdf",
        "tm2321027d15_fwp.htm",
        "filename1.htm",
        "tm2321027-11_f1a.htm",
        "filename1.pdf",
        "filename1.htm",
        "tm2321027-8_f1.htm",
        "filename1.pdf",
        "tm2321027-6_f1.htm",
        "filename1.htm",
        "filename1.htm",
        "filename1.pdf",
        "filename1.htm",
        "filename1.htm",
        "filename1.pdf",
        "filename1.htm"
      ],
      "primaryDocDescription": [
        "424B1",
        "",
        "",
        "F-1",
        "FORM 6-K",
        "FORM S-8",
        "",
        "",
        "",
        "FORM 6-K",
        "FORM 6-K",
        "FORM 6-K",
        "20-F",
        "FORM 6-K",
        "FORM 6-K",
        "FORM 6-K",
        "FORM 6-K",
        "FORM 6-K",
        "SC 13G",
        "SC 13G",
        "SC 13G",
        "FORM 6-K",
        "FORM 6-K",
        "FORM 6-K",
        "424B4",
        "",
        "",
        "FORM 8-A12B",
        "",
        "",
        "F-1/A",
        "",
        "F-1/A",
        "",
        "FWP",
        "",
        "F-1/A",
        "",
        "",
        "F-1/A",
        "",
        "F-1",
        "",
        "",
        "",
        "",
        "",
        "",
        ""
      ]
    },
    "files": []
  }
}